pipme/__init__.py
pipme/check_inits.py
pipme/create_package_setup.py
pipme/get_installed_packages.py
pipme/main.py
pipme-1.3.0.dist-info/METADATA
pipme-1.3.0.dist-info/WHEEL
pipme-1.3.0.dist-info/entry_points.txt
pipme-1.3.0.dist-info/top_level.txt
pipme-1.3.0.dist-info/RECORD
