Metadata-Version: 2.1
Name: pipme
Version: 1.3.0
Requires-Dist: twine >=4.0.2
Requires-Dist: beautifish >=2.2.1
